divoom_gaming_gate/GamingGate.ico
divoom_gaming_gate/__init__.py
divoom_gaming_gate/__main__.py
divoom_gaming_gate/main.py
divoom_gaming_gate/characters/__init__.py
divoom_gaming_gate/characters/character_control.py
divoom_gaming_gate/characters/characters_tab.py
divoom_gaming_gate/designer/__init__.py
divoom_gaming_gate/designer/designer_tab.py
divoom_gaming_gate/designer/editor.html
divoom_gaming_gate/screens/__init__.py
divoom_gaming_gate/screens/screen_control.py
divoom_gaming_gate/screens/screens_tab.py
divoom_gaming_gate/settings/settings_tab.py
divoom_gaming_gate/themes/__init__.py
divoom_gaming_gate/themes/themes_tab.py
divoom_gaming_gate/tools/tools_tab.py
divoom_gaming_gate/utils/__init__.py
divoom_gaming_gate/utils/config.py
divoom_gaming_gate/utils/image.py
divoom_gaming_gate/utils/paths.py
divoom_gaming_gate-0.3.1.dist-info/METADATA
divoom_gaming_gate-0.3.1.dist-info/WHEEL
divoom_gaming_gate-0.3.1.dist-info/entry_points.txt
divoom_gaming_gate-0.3.1.dist-info/top_level.txt
divoom_gaming_gate-0.3.1.dist-info/RECORD
