Metadata-Version: 2.4
Name: divoom-gaming-gate
Version: 0.3.1
Summary: A PyQt5-based character and screen manager for Divoom gaming devices.
Author-email: Your Name <your@email.com>
License-Expression: GPL-3.0-or-later
Requires-Python: >=3.8
Requires-Dist: PyQt5
Requires-Dist: PyQtWebEngine
Requires-Dist: Pillow
Requires-Dist: requests
Requires-Dist: toml
Requires-Dist: appdirs
Requires-Dist: pixellab
